LICENSE
README.md
setup.py
cli/__init__.py
cli/abc.py
cli/app.py
cli/argument.py
cli/command.py
cli/flag.py
cli/help.py
cli/parser.py
cli/wraps.py
cli/tests/__init__.py
cli/tests/app.py
cli/tests/content/__init__.py
cli/tests/content/v1.py
cli/tests/content/v2.py
cli3.egg-info/PKG-INFO
cli3.egg-info/SOURCES.txt
cli3.egg-info/dependency_links.txt
cli3.egg-info/requires.txt
cli3.egg-info/top_level.txt