Metadata-Version: 2.1
Name: cli3
Version: 1.1.2
Summary: A highly configurable, dynamic, fast, and easy solution to managing a command-line application.
Home-page: https://github.com/imgurbot12/cli
Author: Andrew Scott
Author-email: imgurbot12@gmail.com
License: MIT
Classifier: Programming Language :: Python :: 3
Classifier: License :: OSI Approved :: MIT License
Classifier: Operating System :: OS Independent
Requires-Python: >=3.7
License-File: LICENSE
